raw2fits/__init__.py
raw2fits/debayer.py
raw2fits/image.py
raw2fits-1.0.2.dist-info/LICENSE
raw2fits-1.0.2.dist-info/METADATA
raw2fits-1.0.2.dist-info/WHEEL
raw2fits-1.0.2.dist-info/top_level.txt
raw2fits-1.0.2.dist-info/RECORD
