Metadata-Version: 2.1
Name: raw2fits
Version: 1.0.2
Summary: Convert raw images to fits
Home-page: https://github.com/jamiechang917/raw2fits
Author: Jamie Chang
Author-email: jamiechang917@gmail.com
License: MIT
Platform: UNKNOWN
Classifier: Programming Language :: Python :: 3
Classifier: License :: OSI Approved :: MIT License
Classifier: Operating System :: OS Independent
Classifier: Development Status :: 5 - Production/Stable
Classifier: Intended Audience :: Science/Research
Classifier: Topic :: Scientific/Engineering :: Astronomy
Requires-Python: >=3.6
License-File: LICENSE
Requires-Dist: numpy
Requires-Dist: astropy
Requires-Dist: rawpy
Requires-Dist: numba
Requires-Dist: tqdm
Requires-Dist: matplotlib
Requires-Dist: numba-progress
Requires-Dist: exifread
Requires-Dist: opencv-python
